nixos_schema/__init__.py
nixos_schema-0.1.dist-info/METADATA
nixos_schema-0.1.dist-info/WHEEL
nixos_schema-0.1.dist-info/top_level.txt
nixos_schema-0.1.dist-info/RECORD
